npe2/__init__.py
npe2/__main__.py
npe2/_command_registry.py
npe2/_dynamic_plugin.py
npe2/_plugin_manager.py
npe2/_pydantic_compat.py
npe2/_pytest_plugin.py
npe2/_setuptools_plugin.py
npe2/cli.py
npe2/implements.py
npe2/implements.pyi
npe2/io_utils.py
npe2/plugin_manager.py
npe2/py.typed
npe2/types.py
npe2/_inspection/__init__.py
npe2/_inspection/_compile.py
npe2/_inspection/_fetch.py
npe2/_inspection/_from_npe1.py
npe2/_inspection/_setuputils.py
npe2/_inspection/_visitors.py
npe2/manifest/__init__.py
npe2/manifest/_bases.py
npe2/manifest/_npe1_adapter.py
npe2/manifest/_package_metadata.py
npe2/manifest/_validators.py
npe2/manifest/menus.py
npe2/manifest/package_metadata.py
npe2/manifest/schema.py
npe2/manifest/utils.py
npe2/manifest/contributions/__init__.py
npe2/manifest/contributions/_commands.py
npe2/manifest/contributions/_configuration.py
npe2/manifest/contributions/_contributions.py
npe2/manifest/contributions/_icon.py
npe2/manifest/contributions/_json_schema.py
npe2/manifest/contributions/_keybindings.py
npe2/manifest/contributions/_menus.py
npe2/manifest/contributions/_readers.py
npe2/manifest/contributions/_sample_data.py
npe2/manifest/contributions/_submenu.py
npe2/manifest/contributions/_themes.py
npe2/manifest/contributions/_widgets.py
npe2/manifest/contributions/_writers.py
npe2-0.7.7.dist-info/METADATA
npe2-0.7.7.dist-info/WHEEL
npe2-0.7.7.dist-info/entry_points.txt
npe2-0.7.7.dist-info/licenses/LICENSE
npe2-0.7.7.dist-info/RECORD
