Metadata-Version: 2.3
Name: npe2
Version: 0.7.7
Summary: napari plugin engine v2
Project-URL: homepage, https://github.com/napari/npe2
Project-URL: repository, https://github.com/napari/npe2
Author: Nathan Clack
Author-email: Talley Lambert <talley.lambert@gmail.com>
License: BSD-3-Clause
License-File: LICENSE
Classifier: Development Status :: 3 - Alpha
Classifier: License :: OSI Approved :: BSD License
Classifier: Natural Language :: English
Classifier: Programming Language :: Python :: 3
Classifier: Programming Language :: Python :: 3 :: Only
Classifier: Programming Language :: Python :: 3.8
Classifier: Programming Language :: Python :: 3.9
Classifier: Programming Language :: Python :: 3.10
Classifier: Programming Language :: Python :: 3.11
Classifier: Typing :: Typed
Requires-Python: >=3.8
Requires-Dist: appdirs
Requires-Dist: build>=1
Requires-Dist: psygnal>=0.3.0
Requires-Dist: pydantic
Requires-Dist: pyyaml
Requires-Dist: rich
Requires-Dist: tomli-w
Requires-Dist: tomli; python_version < '3.11'
Requires-Dist: typer
Provides-Extra: dev
Requires-Dist: black; extra == 'dev'
Requires-Dist: ipython; extra == 'dev'
Requires-Dist: isort; extra == 'dev'
Requires-Dist: mypy; extra == 'dev'
Requires-Dist: pre-commit; extra == 'dev'
Provides-Extra: docs
Requires-Dist: jinja2; extra == 'docs'
Requires-Dist: magicgui>=0.3.3; extra == 'docs'
Provides-Extra: json
Requires-Dist: jsonschema; extra == 'json'
Provides-Extra: testing
Requires-Dist: jsonschema; extra == 'testing'
Requires-Dist: magicgui; extra == 'testing'
Requires-Dist: napari-plugin-engine; extra == 'testing'
Requires-Dist: napari-svg==0.1.5; extra == 'testing'
Requires-Dist: numpy; extra == 'testing'
Requires-Dist: pytest; extra == 'testing'
Requires-Dist: pytest-cov; extra == 'testing'
Requires-Dist: pytest-pretty; extra == 'testing'
